.gitignore
LICENSE.txt
README.rst
setup.py
tox.ini
docs/api.rst
docs/client.cac.rst
docs/client.rst
docs/conf.py
docs/index.rst
docs/quickstart.rst
examples/caget.py
examples/simple.py
src/channel_access.client.egg-info/PKG-INFO
src/channel_access.client.egg-info/SOURCES.txt
src/channel_access.client.egg-info/dependency_links.txt
src/channel_access.client.egg-info/requires.txt
src/channel_access.client.egg-info/top_level.txt
src/channel_access/client/__init__.py
src/channel_access/client/cac/cac.cpp
src/channel_access/client/cac/cac.hpp
src/channel_access/client/cac/convert.cpp
src/channel_access/client/cac/convert.hpp
src/channel_access/client/cac/pv.cpp
src/channel_access/client/cac/pv.hpp
tests/__init__.py
tests/common.py
tests/conftest.py
tests/test_attributes.py
tests/test_get.py
tests/test_put.py